Metadata-Version: 2.1
Name: schicluster
Version: 1.3.2
Summary: A package for single-cell Hi-C data clustering and downstream analysis.
Home-page: https://github.com/zhoujt1994/scHiCluster
Author: Jingtian Zhou
Author-email: jiz509@eng.ucsd.edu
License: MIT
License-File: LICENSE
